LICENSE.txt
MANIFEST.in
README.md
setup.py
cnn_finetune/__init__.py
cnn_finetune/base.py
cnn_finetune/shims.py
cnn_finetune/utils.py
cnn_finetune.egg-info/PKG-INFO
cnn_finetune.egg-info/SOURCES.txt
cnn_finetune.egg-info/dependency_links.txt
cnn_finetune.egg-info/requires.txt
cnn_finetune.egg-info/top_level.txt
cnn_finetune/contrib/__init__.py
cnn_finetune/contrib/pretrainedmodels.py
cnn_finetune/contrib/torchvision.py