Metadata-Version: 1.2
Name: cnn-finetune
Version: 0.1.6
Summary: Fine-tune pretrained Convolutional Neural Networks with PyTorch
Home-page: https://github.com/creafz/pytorch-cnn-finetune
Author: Alex Parinov
Author-email: creafz@gmail.com
License: MIT
Platform: UNKNOWN
Classifier: Development Status :: 4 - Beta
Classifier: License :: OSI Approved :: MIT License
Classifier: Intended Audience :: Developers
Classifier: Operating System :: OS Independent
Classifier: Programming Language :: Python
Classifier: Programming Language :: Python :: 3
Classifier: Programming Language :: Python :: 3.5
Classifier: Programming Language :: Python :: 3.6
Requires-Python: >=3.5
